setup.py
rest_arch/__init__.py
rest_arch/app.py
rest_arch/async.py
rest_arch/celery_cli.py
rest_arch/client.py
rest_arch/conf.py
rest_arch/consts.py
rest_arch/ctx.py
rest_arch/db.py
rest_arch/exc.py
rest_arch/log.py
rest_arch/mock_queue.py
rest_arch/redis_client.py
rest_arch/service.py
rest_arch/settings.py
rest_arch/signals.py
rest_arch/tracker.py
rest_arch/utils.py
rest_arch.egg-info/PKG-INFO
rest_arch.egg-info/SOURCES.txt
rest_arch.egg-info/dependency_links.txt
rest_arch.egg-info/entry_points.txt
rest_arch.egg-info/requires.txt
rest_arch.egg-info/top_level.txt
rest_arch/skt/__init__.py
rest_arch/skt/config.py
rest_arch/skt/consts.py
rest_arch/skt/env.py
rest_arch/skt/exc.py
rest_arch/skt/log.py
rest_arch/skt/cmds/__init__.py
rest_arch/skt/cmds/serve.py
rest_arch/skt/cmds/shell.py
rest_arch/skt/cmds/bootstrap/__init__.py
rest_arch/skt/runner/__init__.py
rest_arch/skt/runner/hooks.py
tests/__init__.py
tests/test_app.py