Metadata-Version: 1.0
Name: rest-arch
Version: 0.1.4
Summary: A Restful Framework Based On Gunicorn
Home-page: https://github.com/MrKiven/REST_ARCH/
Author: kiven
Author-email: kiven.mr@gmail.com
License: UNKNOWN
Platform: UNKNOWN
